webnovel/__init__.py
webnovel/bot.py
webnovel/cookies.py
webnovel/exceptions.py
webnovel/analytic/__init__.py
webnovel/analytic/analysis.py
webnovel/analytic/crawl.py
webnovel/analytic/efficient.py
webnovel/analytic/hard.py
webnovel/analytic/interface.py
webnovel/api/__init__.py
webnovel/api/base.py
webnovel/api/cookie.py
webnovel/api/html.py
webnovel/api/parsed.py
webnovel/decorators/__init__.py
webnovel/decorators/chainable.py
webnovel/decorators/deprecated.py
webnovel/decorators/interface.py
webnovel/decorators/redirect.py
webnovel/decorators/signin.py
webnovel/handlers/__init__.py
webnovel/handlers/guard.py
webnovel/handlers/handler.py
webnovel/models/__init__.py
webnovel/models/chapter.py
webnovel/models/novel.py
webnovel/models/profile.py
webnovel/tools/__init__.py
webnovel/tools/url.py
webnovelbot-0.3.0.dist-info/LICENSE
webnovelbot-0.3.0.dist-info/METADATA
webnovelbot-0.3.0.dist-info/WHEEL
webnovelbot-0.3.0.dist-info/top_level.txt
webnovelbot-0.3.0.dist-info/RECORD
