Metadata-Version: 2.1
Name: webnovelbot
Version: 0.3.0
Summary: webnovel scraper using selenium
Home-page: https://github.com/mHaisham/webnovelbot
Author: Schicksal
Author-email: mhaisham79@gmail.com
License: MIT license
Project-URL: Source code, https://github.com/mHaisham/webnovelbot
Keywords: webnovel novel bot api
Platform: UNKNOWN
Classifier: License :: OSI Approved :: MIT License
Classifier: Programming Language :: Python :: 3.8
Classifier: Operating System :: OS Independent
Requires-Python: >=3.6
Requires-Dist: requests
Requires-Dist: beautifulsoup4
Requires-Dist: browser-cookie3
Requires-Dist: selenium (==3.141.0)
